task3/ram2ports.sv
module ram2ports # (
    parameter ADDRESS_WIDTH = 8,
              DATA_WIDTH = 8
)(
    input logic clk,
    input logic wr_en,
    input logic rd_en,
    input logic [ADDRESS_WIDTH-1:0] wr_addr,
    input logic [ADDRESS_WIDTH-1:0] rd_addr,
    input logic [DATA_WIDTH-1:0] din,
    output logic [DATA_WIDTH-1:0] dout
);

logic [DATA_WIDTH-1:0] ram_array [2**ADDRESS_WIDTH-1:0];

always_ff @(posedge clk) begin
    if(wr_en == 1'b1)
       ram_array[wr_addr]<= din;
    if(rd_en == 1'b1)
        dout <= ram_array[rd_addr];
    
end

endmodule

task3/adder.sv
module adder#(
    parameter WIDTH = 8
)(
    
    input logic [WIDTH-1:0] a,    //accept counter dout
    input logic [WIDTH-1:0] b,    //accept vbdvalue
    output logic [WIDTH-1:0] sum   //phaser shifted

);

always_comb begin

    sum = a - b;
    
end

endmodule

task3/addrCounter.sv
module addrCounter#(
    parameter WIDTH = 8
)(
    //interface signals
    input logic clk,    //clock
    input logic rst,    //reset
    input logic en,    //counter enable
    input logic [7:0]incr,           //counter inrement
    output logic [WIDTH-1:0] count   //count output
);

always_ff @(posedge clk)
if(rst) count <={WIDTH{1'b0}};
else if(en) count <=count+incr;  

endmodule

task3/sigdelay.sv
module sigdelay #(
  parameter A_WIDTH = 8,
  parameter D_WIDTH = 8
)(
  // interface signals
  input  logic             clk,       // clock 
  input  logic             rst,       // reset 
  input  logic             en,        // counter enable
  input  logic             rd_en,     // read enable
  input  logic             wr_en,     // write enable
  input  logic [A_WIDTH-1:0] incr,    // increment for addr counter
  input  logic [A_WIDTH-1:0] offset,   // signal delay
  input  logic [D_WIDTH-1:0] mic_signal,     // input data
  output logic [D_WIDTH-1:0] delayed_signal    // output data
);

  wire  [A_WIDTH-1:0]       wire1; // interconnect wire1
  wire  [A_WIDTH-1:0]       wire2; // interconnect wire1


addrCounter addrCounter (
  .clk (clk),
  .rst (rst),
  .en (en),
  .incr(incr),
  .count(wire1)
);

adder adder (
  .a (wire1),
  .b (offset),
  .sum (wire2)

);

ram2ports ram2ports (
  .wr_addr (wire1),
  .rd_addr (wire2),
  .din (mic_signal),
  .dout (delayed_signal),
  .wr_en (wr_en),
  .rd_en (rd_en),
  .clk (clk)

);

endmodule

task3/sigdelay.vcd
$version Generated by VerilatedVcd $end
$date Fri Nov  4 11:26:09 2022
 $end
$timescale   1ps $end

 $scope module TOP $end
  $var wire  1 # clk $end
  $var wire  8 + delayed_signal [7:0] $end
  $var wire  1 % en $end
  $var wire  8 ( incr [7:0] $end
  $var wire  8 * mic_signal [7:0] $end
  $var wire  8 ) offset [7:0] $end
  $var wire  1 & rd_en $end
  $var wire  1 $ rst $end
  $var wire  1 ' wr_en $end
  $scope module sigdelay $end
   $var wire 32 . A_WIDTH [31:0] $end
   $var wire 32 . D_WIDTH [31:0] $end
   $var wire  1 # clk $end
   $var wire  8 + delayed_signal [7:0] $end
   $var wire  1 % en $end
   $var wire  8 ( incr [7:0] $end
   $var wire  8 * mic_signal [7:0] $end
   $var wire  8 ) offset [7:0] $end
   $var wire  1 & rd_en $end
   $var wire  1 $ rst $end
   $var wire  8 , wire1 [7:0] $end
   $var wire  8 - wire2 [7:0] $end
   $var wire  1 ' wr_en $end
   $scope module adder $end
    $var wire 32 . WIDTH [31:0] $end
    $var wire  8 , a [7:0] $end
    $var wire  8 ) b [7:0] $end
    $var wire  8 - sum [7:0] $end
   $upscope $end
   $scope module addrCounter $end
    $var wire 32 . WIDTH [31:0] $end
    $var wire  1 # clk $end
    $var wire  8 , count [7:0] $end
    $var wire  1 % en $end
    $var wire  8 ( incr [7:0] $end
    $var wire  1 $ rst $end
   $upscope $end
   $scope module ram2ports $end
    $var wire 32 . ADDRESS_WIDTH [31:0] $end
    $var wire 32 . DATA_WIDTH [31:0] $end
    $var wire  1 # clk $end
    $var wire  8 * din [7:0] $end
    $var wire  8 + dout [7:0] $end
    $var wire  8 - rd_addr [7:0] $end
    $var wire  1 & rd_en $end
    $var wire  8 , wr_addr [7:0] $end
    $var wire  1 ' wr_en $end
   $upscope $end
  $upscope $end
 $upscope $end
$enddefinitions $end


#0
1#
0$
1%
1&
1'
b00000001 (
b00000000 )
b00000000 *
b00000000 +
b00000000 ,
b00000000 -
b00000000000000000000000000001000 .
#1
0#
#2
1#
b00110011 )
b01100000 *
b00000001 ,
b11001110 -
#3
0#
#4
1#
b01011101 *
b00000010 ,
b11001111 -
#5
0#
#6
1#
b01100000 *
b00000011 ,
b11010000 -
#7
0#
#8
1#
b01100011 *
b00000100 ,
b11010001 -
#9
0#
#10
1#
b01101011 *
b00000101 ,
b11010010 -
#11
0#
#12
1#
b01101010 *
b00000110 ,
b11010011 -
#13
0#
#14
1#
b01101111 *
b00000111 ,
b11010100 -
#15
0#
#16
1#
b00001000 ,
b11010101 -
#17
0#
#18
1#
b01110110 *
b00001001 ,
b11010110 -
#19
0#
#20
1#
b10000011 *
b00001010 ,
b11010111 -
#21
0#
#22
1#
b10000110 *
b00001011 ,
b11011000 -
#23
0#
#24
1#
b10001100 *
b00001100 ,
b11011001 -
#25
0#
#26
1#
b10001010 *
b00001101 ,
b11011010 -
#27
0#
#28
1#
b10010100 *
b00001110 ,
b11011011 -
#29
0#
#30
1#
b10010001 *
b00001111 ,
b11011100 -
#31
0#
#32
1#
b10000111 *
b00010000 ,
b11011101 -
#33
0#
#34
1#
b01111101 *
b00010001 ,
b11011110 -
#35
0#
#36
1#
b01101100 *
b00010010 ,
b11011111 -
#37
0#
#38
1#
b01101111 *
b00010011 ,
b11100000 -
#39
0#
#40
1#
b01011110 *
b00010100 ,
b11100001 -
#41
0#
#42
1#
b01011000 *
b00010101 ,
b11100010 -
#43
0#
#44
1#
b01011110 *
b00010110 ,
b11100011 -
#45
0#
#46
1#
b01011011 *
b00010111 ,
b11100100 -
#47
0#
#48
1#
b01101000 *
b00011000 ,
b11100101 -
#49
0#
#50
1#
b01101011 *
b00011001 ,
b11100110 -
#51
0#
#52
1#
b01110010 *
b00011010 ,
b11100111 -
#53
0#
#54
1#
b01110111 *
b00011011 ,
b11101000 -
#55
0#
#56
1#
b01111001 *
b00011100 ,
b11101001 -
#57
0#
#58
1#
b01110001 *
b00011101 ,
b11101010 -
#59
0#
#60
1#
b01111111 *
b00011110 ,
b11101011 -
#61
0#
#62
1#
b10000101 *
b00011111 ,
b11101100 -
#63
0#
#64
1#
b10000001 *
b00100000 ,
b11101101 -
#65
0#
#66
1#
b10001001 *
b00100001 ,
b11101110 -
#67
0#
#68
1#
b10001010 *
b00100010 ,
b11101111 -
#69
0#
#70
1#
b00100011 ,
b11110000 -
#71
0#
#72
1#
b10001110 *
b00100100 ,
b11110001 -
#73
0#
#74
1#
b10010000 *
b00100101 ,
b11110010 -
#75
0#
#76
1#
b10000111 *
b00100110 ,
b11110011 -
#77
0#
#78
1#
b10000001 *
b00100111 ,
b11110100 -
#79
0#
#80
1#
b00101000 ,
b11110101 -
#81
0#
#82
1#
b01110101 *
b00101001 ,
b11110110 -
#83
0#
#84
1#
b01011111 *
b00101010 ,
b11110111 -
#85
0#
#86
1#
b01010011 *
b00101011 ,
b11111000 -
#87
0#
#88
1#
b01010010 *
b00101100 ,
b11111001 -
#89
0#
#90
1#
b01001000 *
b00101101 ,
b11111010 -
#91
0#
#92
1#
b01000000 *
b00101110 ,
b11111011 -
#93
0#
#94
1#
b01000001 *
b00101111 ,
b11111100 -
#95
0#
#96
1#
b01000111 *
b00110000 ,
b11111101 -
#97
0#
#98
1#
b01001101 *
b00110001 ,
b11111110 -
#99
0#
#100
1#
b01010011 *
b00110010 ,
b11111111 -
#101
0#
#102
1#
b01010100 *
b00110011 ,
b00000000 -
#103
0#
#104
1#
b01011111 *
b01100000 +
b00110100 ,
b00000001 -
#105
0#
#106
1#
b01100101 *
b01011101 +
b00110101 ,
b00000010 -
#107
0#
#108
1#
b01100100 *
b01100000 +
b00110110 ,
b00000011 -
#109
0#
#110
1#
b01101001 *
b01100011 +
b00110111 ,
b00000100 -
#111
0#
#112
1#
b01101100 *
b01101011 +
b00111000 ,
b00000101 -
#113
0#
#114
1#
b01110001 *
b01101010 +
b00111001 ,
b00000110 -
#115
0#
#116
1#
b01110010 *
b01101111 +
b00111010 ,
b00000111 -
#117
0#
#118
1#
b00111011 ,
b00001000 -
#119
0#
#120
1#
b01101111 *
b01110110 +
b00111100 ,
b00001001 -
#121
0#
#122
1#
b01011101 *
b10000011 +
b00111101 ,
b00001010 -
#123
0#
#124
1#
b01100101 *
b10000110 +
b00111110 ,
b00001011 -
#125
0#
#126
1#
b10001100 +
b00111111 ,
b00001100 -
#127
0#
#128
1#
b01100100 *
b10001010 +
b01000000 ,
b00001101 -
#129
0#
#130
1#
b01101010 *
b10010100 +
b01000001 ,
b00001110 -
#131
0#
#132
1#
b01110010 *
b10010001 +
b01000010 ,
b00001111 -
#133
0#
#134
1#
b01111111 *
b10000111 +
b01000011 ,
b00010000 -
#135
0#
#136
1#
b10010001 *
b01111101 +
b01000100 ,
b00010001 -
#137
0#
#138
1#
b10001111 *
b01101100 +
b01000101 ,
b00010010 -
#139
0#
#140
1#
b01101111 +
b01000110 ,
b00010011 -
#141
0#
#142
1#
b10011000 *
b01011110 +
b01000111 ,
b00010100 -
#143
0#
#144
1#
b10010010 *
b01011000 +
b01001000 ,
b00010101 -
#145
0#
#146
1#
b10000010 *
b01011110 +
b01001001 ,
b00010110 -
#147
0#
#148
1#
b01110001 *
b01011011 +
b01001010 ,
b00010111 -
#149
0#
#150
1#
b01100110 *
b01101000 +
b01001011 ,
b00011000 -
#151
0#
#152
1#
b01100101 *
b01101011 +
b01001100 ,
b00011001 -
#153
0#
#154
1#
b01010110 *
b01110010 +
b01001101 ,
b00011010 -
#155
0#
#156
1#
b01010000 *
b01110111 +
b01001110 ,
b00011011 -
#157
0#
#158
1#
b01010010 *
b01111001 +
b01001111 ,
b00011100 -
#159
0#
#160
1#
b01010111 *
b01110001 +
b01010000 ,
b00011101 -
#161
0#
#162
1#
b01010011 *
b01111111 +
b01010001 ,
b00011110 -
#163
0#
#164
1#
b01001011 *
b10000101 +
b01010010 ,
b00011111 -
#165
0#
#166
1#
b01001111 *
b10000001 +
b01010011 ,
b00100000 -
#167
0#
#168
1#
b01010000 *
b10001001 +
b01010100 ,
b00100001 -
#169
0#
#170
1#
b01011011 *
b10001010 +
b01010101 ,
b00100010 -
#171
0#
#172
1#
b01011100 *
b01010110 ,
b00100011 -
#173
0#
#174
1#
b01010011 *
b10001110 +
b01010111 ,
b00100100 -
#175
0#
#176
1#
b01010111 *
b10010000 +
b01011000 ,
b00100101 -
#177
0#
#178
1#
b01011111 *
b10000111 +
b01011001 ,
b00100110 -
#179
0#
#180
1#
b01100110 *
b10000001 +
b01011010 ,
b00100111 -
#181
0#
#182
1#
b01100101 *
b01011011 ,
b00101000 -
#183
0#
#184
1#
b01101101 *
b01110101 +
b01011100 ,
b00101001 -
#185
0#
#186
1#
b01110101 *
b01011111 +
b01011101 ,
b00101010 -
#187
0#
#188
1#
b01111010 *
b01010011 +
b01011110 ,
b00101011 -
#189
0#
#190
1#
b01111110 *
b01010010 +
b01011111 ,
b00101100 -
#191
0#
#192
1#
b10000001 *
b01001000 +
b01100000 ,
b00101101 -
#193
0#
#194
1#
b01111110 *
b01000000 +
b01100001 ,
b00101110 -
#195
0#
#196
1#
b01111111 *
b01000001 +
b01100010 ,
b00101111 -
#197
0#
#198
1#
b10000000 *
b01000111 +
b01100011 ,
b00110000 -
