task2/rom2ports.sv
module rom2ports #(
    parameter ADDRESS_WIDTH = 8,
              DATA_WIDTH = 8
)(
    input logic clk,
    input logic [ADDRESS_WIDTH-1:0] addr1,
    input logic [ADDRESS_WIDTH-1:0] addr2,
    output logic [DATA_WIDTH-1:0] dout1,
    output logic [DATA_WIDTH-1:0] dout2
);

logic [DATA_WIDTH-1:0] rom_array [2**ADDRESS_WIDTH-1:0];

initial begin
    $display("Loading rom.");
    $readmemh("sinerom.mem",rom_array);
end;

always_ff @(posedge clk) begin
    //output is synchronous
    dout1 <= rom_array [addr1];
    dout2 <= rom_array [addr2];

end

endmodule

task2/adder.sv
module adder#(
    parameter WIDTH = 8
)(
    
    input logic [WIDTH-1:0] a,    //accept counter dout
    input logic [WIDTH-1:0] b,    //accept vbdvalue
    output logic [WIDTH-1:0] sum   //phaser shifted

);

always_comb begin

    sum = a + b;
    
end

endmodule

task3/addrCounter.sv
module addrCounter#(
    parameter WIDTH = 8
)(
    //interface signals
    input logic clk,    //clock
    input logic rst,    //reset
    input logic en,    //counter enable
    input logic [7:0]incr,           //counter inrement
    output logic [WIDTH-1:0] count   //count output
);

always_ff @(posedge clk)
if(rst) count <={WIDTH{1'b0}};
else if(en) count <=count+incr;  

endmodule

task2/top.sv
module top #(
  parameter A_WIDTH = 8,
  parameter D_WIDTH = 8
)(
  // interface signals
  input  wire             clk,      // clock 
  input  wire             rst,      // reset 
  input  wire             en,       // enable
  input  wire [D_WIDTH-1:0] incr,   // increment for addr counter
  input  wire [D_WIDTH-1:0] offset, // offset
  output wire [D_WIDTH-1:0] dout1,    // output data
  output wire [D_WIDTH-1:0] dout2    // output data
);

  wire  [A_WIDTH-1:0]       address;  // interconnect wire1
  wire  [A_WIDTH-1:0]       wire1;    // interconnect counter and adder/rom
  wire  [A_WIDTH-1:0]       wire2;    // interconnect adder and rom2ports


addrCounter addrCounter (
  .clk (clk),
  .rst (rst),
  .en (en),
  .incr(incr),
  .count(wire1)
);

adder adder(
  .a (wire1),
  .b (offset),
  .sum (wire2)
);

rom2ports rom2ports(
  .clk(clk),
  .addr1(wire1),
  .addr2(wire2),
  .dout1(dout1),
  .dout2(dout2)
);

endmodule

task2/sinegen.vcd
$version Generated by VerilatedVcd $end
$date Fri Oct 28 18:25:36 2022
 $end
$timescale   1ps $end

 $scope module TOP $end
  $var wire  1 # clk $end
  $var wire  8 ( dout1 [7:0] $end
  $var wire  8 ) dout2 [7:0] $end
  $var wire  1 % en $end
  $var wire  8 & incr [7:0] $end
  $var wire  8 ' offset [7:0] $end
  $var wire  1 $ rst $end
  $scope module top $end
   $var wire 32 , A_WIDTH [31:0] $end
   $var wire 32 , D_WIDTH [31:0] $end
   $var wire  8 - address [7:0] $end
   $var wire  1 # clk $end
   $var wire  8 ( dout1 [7:0] $end
   $var wire  8 ) dout2 [7:0] $end
   $var wire  1 % en $end
   $var wire  8 & incr [7:0] $end
   $var wire  8 ' offset [7:0] $end
   $var wire  1 $ rst $end
   $var wire  8 * wire1 [7:0] $end
   $var wire  8 + wire2 [7:0] $end
   $scope module adder $end
    $var wire 32 , WIDTH [31:0] $end
    $var wire  8 * a [7:0] $end
    $var wire  8 ' b [7:0] $end
    $var wire  8 + sum [7:0] $end
   $upscope $end
   $scope module addrCounter $end
    $var wire 32 , WIDTH [31:0] $end
    $var wire  1 # clk $end
    $var wire  8 * count [7:0] $end
    $var wire  1 % en $end
    $var wire  8 & incr [7:0] $end
    $var wire  1 $ rst $end
   $upscope $end
   $scope module rom2ports $end
    $var wire 32 , ADDRESS_WIDTH [31:0] $end
    $var wire 32 , DATA_WIDTH [31:0] $end
    $var wire  8 * addr1 [7:0] $end
    $var wire  8 + addr2 [7:0] $end
    $var wire  1 # clk $end
    $var wire  8 ( dout1 [7:0] $end
    $var wire  8 ) dout2 [7:0] $end
   $upscope $end
  $upscope $end
 $upscope $end
$enddefinitions $end


#0
1#
0$
1%
b00000001 &
b00000000 '
b00000000 (
b00000000 )
b00000000 *
b00000000 +
b00000000000000000000000000001000 ,
b00000000 -
#1
0#
#2
1#
0%
b00110011 '
b11111110 (
b11111110 )
b00000001 *
b00110100 +
#3
0#
#4
1#
b11111101 (
b10100011 )
#5
0#
#6
1#
#7
0#
#8
1#
#9
0#
#10
1#
#11
0#
#12
1#
#13
0#
#14
1#
#15
0#
#16
1#
#17
0#
#18
1#
#19
0#
#20
1#
#21
0#
#22
1#
#23
0#
#24
1#
#25
0#
#26
1#
#27
0#
#28
1#
#29
0#
#30
1#
#31
0#
#32
1#
#33
0#
#34
1#
#35
0#
#36
1#
#37
0#
#38
1#
#39
0#
#40
1#
#41
0#
#42
1#
#43
0#
#44
1#
#45
0#
#46
1#
#47
0#
#48
1#
#49
0#
#50
1#
#51
0#
#52
1#
#53
0#
#54
1#
#55
0#
#56
1#
#57
0#
#58
1#
#59
0#
#60
1#
#61
0#
#62
1#
#63
0#
#64
1#
#65
0#
#66
1#
#67
0#
#68
1#
#69
0#
#70
1#
#71
0#
#72
1#
#73
0#
#74
1#
#75
0#
#76
1#
#77
0#
#78
1#
#79
0#
#80
1#
#81
0#
#82
1#
#83
0#
#84
1#
#85
0#
#86
1#
#87
0#
#88
1#
#89
0#
#90
1#
#91
0#
#92
1#
#93
0#
#94
1#
#95
0#
#96
1#
#97
0#
#98
1#
#99
0#
#100
1#
#101
0#
#102
1#
#103
0#
#104
1#
#105
0#
#106
1#
#107
0#
#108
1#
#109
0#
#110
1#
#111
0#
#112
1#
#113
0#
#114
1#
#115
0#
#116
1#
#117
0#
#118
1#
#119
0#
#120
1#
#121
0#
#122
1#
#123
0#
#124
1#
#125
0#
#126
1#
#127
0#
#128
1#
#129
0#
#130
1#
#131
0#
#132
1#
#133
0#
#134
1#
#135
0#
#136
1#
#137
0#
#138
1#
#139
0#
#140
1#
#141
0#
#142
1#
#143
0#
#144
1#
#145
0#
#146
1#
#147
0#
#148
1#
#149
0#
#150
1#
#151
0#
#152
1#
#153
0#
#154
1#
#155
0#
#156
1#
#157
0#
#158
1#
#159
0#
#160
1#
#161
0#
#162
1#
#163
0#
#164
1#
#165
0#
#166
1#
#167
0#
#168
1#
#169
0#
#170
1#
#171
0#
#172
1#
#173
0#
#174
1#
#175
0#
#176
1#
#177
0#
#178
1#
b00110100 '
b00110101 +
#179
0#
#180
1#
b00110101 '
b10100000 )
b00110110 +
#181
0#
#182
1#
b00110110 '
b10011101 )
b00110111 +
#183
0#
#184
1#
b00110111 '
b10011010 )
b00111000 +
#185
0#
#186
1#
b00111100 '
b10010111 )
b00111101 +
#187
0#
#188
1#
b00111111 '
b10001000 )
b01000000 +
#189
0#
#190
1#
b01000000 '
b01111110 )
b01000001 +
#191
0#
#192
1#
b01000001 '
b01111011 )
b01000010 +
#193
0#
#194
1#
b01000010 '
b01111000 )
b01000011 +
#195
0#
#196
1#
b01000011 '
b01110101 )
b01000100 +
#197
0#
#198
1#
b01000101 '
b01110010 )
b01000110 +
#199
0#
#200
1#
b01101100 )
#201
0#
#202
1#
b01000110 '
b01000111 +
#203
0#
#204
1#
b01101001 )
