task2/rom2ports.sv
module rom2ports #(
    parameter ADDRESS_WIDTH = 8,
              DATA_WIDTH = 8
)(
    input logic clk,
    input logic [ADDRESS_WIDTH-1:0] addr1,
    input logic [ADDRESS_WIDTH-1:0] addr2,
    output logic [DATA_WIDTH-1:0] dout1,
    output logic [DATA_WIDTH-1:0] dout2
);

logic [DATA_WIDTH-1:0] rom_array [2**ADDRESS_WIDTH-1:0];

initial begin
    $display("Loading rom.");
    $readmemh("sinerom.mem",rom_array);
end;

always_ff @(posedge clk) begin
    //output is synchronous
    dout1 <= rom_array [addr1];
    dout2 <= rom_array [addr2];

end

endmodule

task2/adder.sv
module adder#(
    parameter WIDTH = 8
)(
    
    input logic [WIDTH-1:0] a,    //accept counter dout
    input logic [WIDTH-1:0] b,    //accept vbdvalue
    output logic [WIDTH-1:0] sum   //phaser shifted

);

always_comb begin

    sum = a + b;
    
end

endmodule

task3/addrCounter.sv
module addrCounter#(
    parameter WIDTH = 8
)(
    //interface signals
    input logic clk,    //clock
    input logic rst,    //reset
    input logic en,    //counter enable
    input logic [7:0]incr,           //counter inrement
    output logic [WIDTH-1:0] count   //count output
);

always_ff @(posedge clk)
if(rst) count <={WIDTH{1'b0}};
else if(en) count <=count+incr;  

endmodule

task2/top.sv
module top #(
  parameter A_WIDTH = 8,
  parameter D_WIDTH = 8
)(
  // interface signals
  input  wire             clk,      // clock 
  input  wire             rst,      // reset 
  input  wire             en,       // enable
  input  wire [D_WIDTH-1:0] incr,   // increment for addr counter
  input  wire [D_WIDTH-1:0] offset, // offset
  output wire [D_WIDTH-1:0] dout1,    // output data
  output wire [D_WIDTH-1:0] dout2    // output data
);

  wire  [A_WIDTH-1:0]       address;  // interconnect wire1
  wire  [A_WIDTH-1:0]       wire1;    // interconnect counter and adder/rom
  wire  [A_WIDTH-1:0]       wire2;    // interconnect adder and rom2ports


addrCounter addrCounter (
  .clk (clk),
  .rst (rst),
  .en (en),
  .incr(incr),
  .count(wire1)
);

adder adder(
  .a (wire1),
  .b (offset),
  .sum (wire2)
);

rom2ports rom2ports(
  .clk(clk),
  .addr1(wire1),
  .addr2(wire2),
  .dout1(dout1),
  .dout2(dout2)
);

endmodule

task2/sinegen.vcd
$version Generated by VerilatedVcd $end
$date Fri Oct 28 13:10:00 2022
 $end
$timescale   1ps $end

 $scope module TOP $end
  $var wire  1 # clk $end
  $var wire  8 ( dout1 [7:0] $end
  $var wire  8 ) dout2 [7:0] $end
  $var wire  1 % en $end
  $var wire  8 & incr [7:0] $end
  $var wire  8 ' offset [7:0] $end
  $var wire  1 $ rst $end
  $scope module top $end
   $var wire 32 , A_WIDTH [31:0] $end
   $var wire 32 , D_WIDTH [31:0] $end
   $var wire  8 - address [7:0] $end
   $var wire  1 # clk $end
   $var wire  8 ( dout1 [7:0] $end
   $var wire  8 ) dout2 [7:0] $end
   $var wire  1 % en $end
   $var wire  8 & incr [7:0] $end
   $var wire  8 ' offset [7:0] $end
   $var wire  1 $ rst $end
   $var wire  8 * wire1 [7:0] $end
   $var wire  8 + wire2 [7:0] $end
   $scope module adder $end
    $var wire 32 , WIDTH [31:0] $end
    $var wire  8 * a [7:0] $end
    $var wire  8 ' b [7:0] $end
    $var wire  8 + sum [7:0] $end
   $upscope $end
   $scope module addrCounter $end
    $var wire 32 , WIDTH [31:0] $end
    $var wire  1 # clk $end
    $var wire  8 * count [7:0] $end
    $var wire  1 % en $end
    $var wire  8 & incr [7:0] $end
    $var wire  1 $ rst $end
   $upscope $end
   $scope module rom2ports $end
    $var wire 32 , ADDRESS_WIDTH [31:0] $end
    $var wire 32 , DATA_WIDTH [31:0] $end
    $var wire  8 * addr1 [7:0] $end
    $var wire  8 + addr2 [7:0] $end
    $var wire  1 # clk $end
    $var wire  8 ( dout1 [7:0] $end
    $var wire  8 ) dout2 [7:0] $end
   $upscope $end
  $upscope $end
 $upscope $end
$enddefinitions $end


#0
1#
0$
1%
b00000001 &
b00000000 '
b00000000 (
b00000000 )
b00000000 *
b00000000 +
b00000000000000000000000000001000 ,
b00000000 -
#1
0#
#2
1#
0%
b01000000 '
b11111110 (
b11111110 )
b00000001 *
b01000001 +
#3
0#
#4
1#
b11111101 (
b01111011 )
#5
0#
#6
1#
#7
0#
#8
1#
#9
0#
#10
1#
#11
0#
#12
1#
#13
0#
#14
1#
#15
0#
#16
1#
#17
0#
#18
1#
#19
0#
#20
1#
#21
0#
#22
1#
#23
0#
#24
1#
#25
0#
#26
1#
#27
0#
#28
1#
#29
0#
#30
1#
#31
0#
#32
1#
#33
0#
#34
1#
#35
0#
#36
1#
#37
0#
#38
1#
#39
0#
#40
1#
#41
0#
#42
1#
#43
0#
#44
1#
#45
0#
#46
1#
#47
0#
#48
1#
#49
0#
#50
1#
#51
0#
#52
1#
#53
0#
#54
1#
#55
0#
#56
1#
#57
0#
#58
1#
#59
0#
#60
1#
#61
0#
#62
1#
#63
0#
#64
1#
#65
0#
#66
1#
#67
0#
#68
1#
#69
0#
#70
1#
#71
0#
#72
1#
#73
0#
#74
1#
#75
0#
#76
1#
#77
0#
#78
1#
#79
0#
#80
1#
#81
0#
#82
1#
#83
0#
#84
1#
#85
0#
#86
1#
#87
0#
#88
1#
#89
0#
#90
1#
#91
0#
#92
1#
#93
0#
#94
1#
#95
0#
#96
1#
#97
0#
#98
1#
#99
0#
#100
1#
#101
0#
#102
1#
#103
0#
#104
1#
#105
0#
#106
1#
#107
0#
#108
1#
#109
0#
#110
1#
#111
0#
#112
1#
#113
0#
#114
1#
#115
0#
#116
1#
#117
0#
#118
1#
#119
0#
#120
1#
#121
0#
#122
1#
#123
0#
#124
1#
#125
0#
#126
1#
#127
0#
#128
1#
#129
0#
#130
1#
#131
0#
#132
1#
#133
0#
#134
1#
#135
0#
#136
1#
#137
0#
#138
1#
#139
0#
#140
1#
#141
0#
#142
1#
#143
0#
#144
1#
#145
0#
#146
1#
#147
0#
#148
1#
#149
0#
#150
1#
#151
0#
#152
1#
#153
0#
#154
1#
#155
0#
#156
1#
#157
0#
#158
1#
#159
0#
#160
1#
#161
0#
#162
1#
#163
0#
#164
1#
#165
0#
#166
1#
#167
0#
#168
1#
#169
0#
#170
1#
#171
0#
#172
1#
#173
0#
#174
1#
#175
0#
#176
1#
#177
0#
#178
1#
#179
0#
#180
1#
#181
0#
#182
1#
#183
0#
#184
1#
#185
0#
#186
1#
#187
0#
#188
1#
#189
0#
#190
1#
#191
0#
#192
1#
#193
0#
#194
1#
#195
0#
#196
1#
#197
0#
#198
1#
#199
0#
#200
1#
#201
0#
#202
1#
#203
0#
#204
1#
#205
0#
#206
1#
#207
0#
#208
1#
#209
0#
#210
1#
#211
0#
#212
1#
#213
0#
#214
1#
#215
0#
#216
1#
#217
0#
#218
1#
#219
0#
#220
1#
#221
0#
#222
1#
#223
0#
#224
1#
#225
0#
#226
1#
#227
0#
#228
1#
#229
0#
#230
1#
#231
0#
#232
1#
#233
0#
#234
1#
#235
0#
#236
1#
#237
0#
#238
1#
#239
0#
#240
1#
#241
0#
#242
1#
#243
0#
#244
1#
#245
0#
#246
1#
#247
0#
#248
1#
#249
0#
#250
1#
#251
0#
#252
1#
#253
0#
#254
1#
#255
0#
#256
1#
#257
0#
#258
1#
#259
0#
#260
1#
#261
0#
#262
1#
#263
0#
#264
1#
#265
0#
#266
1#
#267
0#
#268
1#
#269
0#
#270
1#
b00111101 '
b00111110 +
#271
0#
#272
1#
b00111011 '
b10000101 )
b00111100 +
#273
0#
#274
1#
b00111000 '
b10001011 )
b00111001 +
#275
0#
#276
1#
b10010100 )
#277
0#
#278
1#
#279
0#
#280
1#
#281
0#
#282
1#
#283
0#
#284
1#
#285
0#
#286
1#
#287
0#
#288
1#
#289
0#
#290
1#
#291
0#
#292
1#
#293
0#
#294
1#
#295
0#
#296
1#
#297
0#
#298
1#
#299
0#
#300
1#
#301
0#
#302
1#
#303
0#
#304
1#
#305
0#
#306
1#
#307
0#
#308
1#
#309
0#
#310
1#
#311
0#
#312
1#
#313
0#
#314
1#
#315
0#
#316
1#
#317
0#
#318
1#
#319
0#
#320
1#
#321
0#
#322
1#
#323
0#
#324
1#
#325
0#
#326
1#
#327
0#
#328
1#
#329
0#
#330
1#
#331
0#
#332
1#
#333
0#
#334
1#
#335
0#
#336
1#
#337
0#
#338
1#
#339
0#
#340
1#
#341
0#
#342
1#
#343
0#
#344
1#
#345
0#
#346
1#
#347
0#
#348
1#
#349
0#
#350
1#
#351
0#
#352
1#
#353
0#
#354
1#
#355
0#
#356
1#
#357
0#
#358
1#
#359
0#
#360
1#
#361
0#
#362
1#
#363
0#
#364
1#
#365
0#
#366
1#
#367
0#
#368
1#
#369
0#
#370
1#
#371
0#
#372
1#
#373
0#
#374
1#
#375
0#
#376
1#
#377
0#
#378
1#
#379
0#
#380
1#
#381
0#
#382
1#
#383
0#
#384
1#
#385
0#
#386
1#
#387
0#
#388
1#
#389
0#
#390
1#
#391
0#
#392
1#
#393
0#
#394
1#
#395
0#
#396
1#
#397
0#
#398
1#
#399
0#
#400
1#
#401
0#
#402
1#
#403
0#
#404
1#
#405
0#
#406
1#
#407
0#
#408
1#
#409
0#
#410
1#
#411
0#
#412
1#
#413
0#
#414
1#
#415
0#
#416
1#
#417
0#
#418
1#
#419
0#
#420
1#
#421
0#
#422
1#
#423
0#
#424
1#
#425
0#
#426
1#
#427
0#
#428
1#
#429
0#
#430
1#
#431
0#
#432
1#
#433
0#
#434
1#
#435
0#
#436
1#
#437
0#
#438
1#
#439
0#
#440
1#
#441
0#
#442
1#
#443
0#
#444
1#
#445
0#
#446
1#
#447
0#
#448
1#
#449
0#
#450
1#
#451
0#
#452
1#
#453
0#
#454
1#
#455
0#
#456
1#
#457
0#
#458
1#
#459
0#
#460
1#
#461
0#
#462
1#
#463
0#
#464
1#
#465
0#
#466
1#
#467
0#
#468
1#
#469
0#
#470
1#
#471
0#
#472
1#
#473
0#
#474
1#
#475
0#
#476
1#
#477
0#
#478
1#
#479
0#
#480
1#
#481
0#
#482
1#
#483
0#
#484
1#
#485
0#
#486
1#
#487
0#
#488
1#
#489
0#
#490
1#
#491
0#
#492
1#
#493
0#
#494
1#
#495
0#
#496
1#
#497
0#
#498
1#
#499
0#
#500
1#
#501
0#
#502
1#
#503
0#
#504
1#
#505
0#
#506
1#
#507
0#
#508
1#
#509
0#
#510
1#
#511
0#
#512
1#
#513
0#
#514
1#
#515
0#
#516
1#
#517
0#
#518
1#
#519
0#
#520
1#
#521
0#
#522
1#
#523
0#
#524
1#
#525
0#
#526
1#
#527
0#
#528
1#
#529
0#
#530
1#
#531
0#
#532
1#
#533
0#
#534
1#
#535
0#
#536
1#
#537
0#
#538
1#
#539
0#
#540
1#
#541
0#
#542
1#
#543
0#
#544
1#
#545
0#
#546
1#
#547
0#
#548
1#
#549
0#
#550
1#
#551
0#
#552
1#
#553
0#
#554
1#
#555
0#
#556
1#
#557
0#
#558
1#
#559
0#
#560
1#
#561
0#
#562
1#
#563
0#
#564
1#
#565
0#
#566
1#
#567
0#
#568
1#
#569
0#
#570
1#
#571
0#
#572
1#
#573
0#
#574
1#
#575
0#
#576
1#
#577
0#
#578
1#
#579
0#
#580
1#
#581
0#
#582
1#
#583
0#
#584
1#
#585
0#
#586
1#
#587
0#
#588
1#
#589
0#
#590
1#
#591
0#
#592
1#
#593
0#
#594
1#
#595
0#
#596
1#
#597
0#
#598
1#
#599
0#
#600
1#
#601
0#
#602
1#
#603
0#
#604
1#
#605
0#
#606
1#
#607
0#
#608
1#
#609
0#
#610
1#
#611
0#
#612
1#
#613
0#
#614
1#
#615
0#
#616
1#
#617
0#
#618
1#
#619
0#
#620
1#
#621
0#
#622
1#
#623
0#
#624
1#
#625
0#
#626
1#
#627
0#
#628
1#
#629
0#
#630
1#
#631
0#
#632
1#
#633
0#
#634
1#
#635
0#
#636
1#
#637
0#
#638
1#
#639
0#
#640
1#
#641
0#
#642
1#
#643
0#
#644
1#
#645
0#
#646
1#
#647
0#
#648
1#
#649
0#
#650
1#
#651
0#
#652
1#
#653
0#
#654
1#
#655
0#
#656
1#
#657
0#
#658
1#
#659
0#
#660
1#
#661
0#
#662
1#
#663
0#
#664
1#
#665
0#
#666
1#
#667
0#
#668
1#
#669
0#
#670
1#
#671
0#
#672
1#
#673
0#
#674
1#
#675
0#
#676
1#
1%
#677
0#
#678
1#
b00000010 *
b00111010 +
#679
0#
#680
1#
b10010001 )
b00000011 *
b00111011 +
#681
0#
#682
1#
b10001110 )
b00000100 *
b00111100 +
#683
0#
#684
1#
b10001011 )
b00000101 *
b00111101 +
#685
0#
#686
1#
b10001000 )
b00000110 *
b00111110 +
#687
0#
#688
1#
b11111100 (
b10000101 )
b00000111 *
b00111111 +
#689
0#
#690
1#
b10000010 )
b00001000 *
b01000000 +
#691
0#
#692
1#
b11111011 (
b01111110 )
b00001001 *
b01000001 +
#693
0#
#694
1#
b11111010 (
b01111011 )
b00001010 *
b01000010 +
#695
0#
#696
1#
b01111000 )
b00001011 *
b01000011 +
#697
0#
#698
1#
b11111001 (
b01110101 )
b00001100 *
b01000100 +
#699
0#
#700
1#
b11111000 (
b01110010 )
b00001101 *
b01000101 +
#701
0#
#702
1#
b11110111 (
b01101111 )
b00001110 *
b01000110 +
#703
0#
#704
1#
b11110110 (
b01101100 )
b00001111 *
b01000111 +
#705
0#
#706
1#
b11110101 (
b01101001 )
b00010000 *
b01001000 +
#707
0#
#708
1#
b11110100 (
b01100110 )
b00010001 *
b01001001 +
#709
0#
#710
1#
b11110011 (
b01100011 )
b00010010 *
b01001010 +
#711
0#
#712
1#
b11110001 (
b01100000 )
b00010011 *
b01001011 +
#713
0#
#714
1#
b11110000 (
b01011101 )
b00010100 *
b01001100 +
#715
0#
#716
1#
b11101111 (
b01011010 )
b00010101 *
b01001101 +
#717
0#
#718
1#
b11101101 (
b01010111 )
b00010110 *
b01001110 +
#719
0#
#720
1#
b11101011 (
b01010100 )
b00010111 *
b01001111 +
#721
0#
#722
1#
b11101010 (
b01010001 )
b00011000 *
b01010000 +
#723
0#
#724
1#
b11101000 (
b01001110 )
b00011001 *
b01010001 +
#725
0#
#726
1#
b11100110 (
b01001011 )
b00011010 *
b01010010 +
#727
0#
#728
1#
b11100101 (
b01001000 )
b00011011 *
b01010011 +
#729
0#
#730
1#
b11100011 (
b01000101 )
b00011100 *
b01010100 +
#731
0#
#732
1#
b11100001 (
b01000011 )
b00011101 *
b01010101 +
#733
0#
#734
1#
b11011111 (
b01000000 )
b00011110 *
b01010110 +
#735
0#
#736
1#
b11011101 (
b00111101 )
b00011111 *
b01010111 +
#737
0#
#738
1#
b11011010 (
b00111011 )
b00100000 *
b01011000 +
#739
0#
#740
1#
b11011000 (
b00111000 )
b00100001 *
b01011001 +
#741
0#
#742
1#
b11010110 (
b00110101 )
b00100010 *
b01011010 +
#743
0#
#744
1#
b11010100 (
b00110011 )
b00100011 *
b01011011 +
#745
0#
#746
1#
b11010001 (
b00110000 )
b00100100 *
b01011100 +
#747
0#
#748
1#
b11001111 (
b00101110 )
b00100101 *
b01011101 +
#749
0#
#750
1#
b11001101 (
b00101100 )
b00100110 *
b01011110 +
#751
0#
#752
1#
b11001010 (
b00101001 )
b00100111 *
b01011111 +
#753
0#
#754
1#
b11001000 (
b00100111 )
b00101000 *
b01100000 +
#755
0#
#756
1#
b11000101 (
b00100101 )
b00101001 *
b01100001 +
#757
0#
#758
1#
b11000010 (
b00100011 )
b00101010 *
b01100010 +
#759
0#
#760
1#
b11000000 (
b00100000 )
b00101011 *
b01100011 +
#761
0#
#762
1#
b10111101 (
b00011110 )
b00101100 *
b01100100 +
#763
0#
#764
1#
b10111010 (
b00011100 )
b00101101 *
b01100101 +
#765
0#
#766
1#
b10111000 (
b00011010 )
b00101110 *
b01100110 +
#767
0#
#768
1#
b10110101 (
b00011000 )
b00101111 *
b01100111 +
#769
0#
#770
1#
b10110010 (
b00010111 )
b00110000 *
b01101000 +
#771
0#
#772
1#
b10101111 (
b00010101 )
b00110001 *
b01101001 +
#773
0#
#774
1#
b10101100 (
b00010011 )
b00110010 *
b01101010 +
#775
0#
#776
1#
b10101001 (
b00010010 )
b00110011 *
b01101011 +
#777
0#
#778
1#
b10100110 (
b00010000 )
b00110100 *
b01101100 +
#779
0#
#780
1#
b10100011 (
b00001110 )
b00110101 *
b01101101 +
#781
0#
#782
1#
b10100000 (
b00001101 )
b00110110 *
b01101110 +
#783
0#
#784
1#
b10011101 (
b00001100 )
b00110111 *
b01101111 +
#785
0#
#786
1#
b10011010 (
b00001010 )
b00111000 *
b01110000 +
#787
0#
#788
1#
b10010111 (
b00001001 )
b00111001 *
b01110001 +
#789
0#
#790
1#
b10010100 (
b00001000 )
b00111010 *
b01110010 +
#791
0#
#792
1#
b10010001 (
b00000111 )
b00111011 *
b01110011 +
#793
0#
#794
1#
b10001110 (
b00000110 )
b00111100 *
b01110100 +
#795
0#
#796
1#
b10001011 (
b00000101 )
b00111101 *
b01110101 +
#797
0#
#798
1#
b10001000 (
b00000100 )
b00111110 *
b01110110 +
#799
0#
#800
1#
b10000101 (
b00000011 )
b00111111 *
b01110111 +
#801
0#
#802
1#
b10000010 (
b01000000 *
b01111000 +
#803
0#
#804
1#
b01111110 (
b00000010 )
b01000001 *
b01111001 +
#805
0#
#806
1#
b01111011 (
b00000001 )
b01000010 *
b01111010 +
#807
0#
#808
1#
b01111000 (
b01000011 *
b01111011 +
#809
0#
#810
1#
b01110101 (
b00000000 )
b01000100 *
b01111100 +
#811
0#
#812
1#
b01110010 (
b01000101 *
b01111101 +
#813
0#
#814
1#
b01101111 (
b01000110 *
b01111110 +
#815
0#
#816
1#
b01101100 (
b01000111 *
b01111111 +
#817
0#
#818
1#
b01101001 (
b01001000 *
b10000000 +
#819
0#
#820
1#
b01100110 (
b01001001 *
b10000001 +
#821
0#
#822
1#
b01100011 (
b01001010 *
b10000010 +
#823
0#
#824
1#
b01100000 (
b01001011 *
b10000011 +
#825
0#
#826
1#
b01011101 (
b01001100 *
b10000100 +
#827
0#
#828
1#
b01011010 (
b01001101 *
b10000101 +
#829
0#
#830
1#
b01010111 (
b01001110 *
b10000110 +
#831
0#
#832
1#
b01010100 (
b00000001 )
b01001111 *
b10000111 +
#833
0#
#834
1#
b01010001 (
b01010000 *
b10001000 +
#835
0#
#836
1#
b01001110 (
b00000010 )
b01010001 *
b10001001 +
#837
0#
#838
1#
b01001011 (
b00000011 )
b01010010 *
b10001010 +
#839
0#
#840
1#
b01001000 (
b01010011 *
b10001011 +
#841
0#
#842
1#
b01000101 (
b00000100 )
b01010100 *
b10001100 +
#843
0#
#844
1#
b01000011 (
b00000101 )
b01010101 *
b10001101 +
#845
0#
#846
1#
b01000000 (
b00000110 )
b01010110 *
b10001110 +
#847
0#
#848
1#
b00111101 (
b00000111 )
b01010111 *
b10001111 +
#849
0#
#850
1#
b00111011 (
b00001000 )
b01011000 *
b10010000 +
#851
0#
#852
1#
b00111000 (
b00001001 )
b01011001 *
b10010001 +
#853
0#
#854
1#
b00110101 (
b00001010 )
b01011010 *
b10010010 +
#855
0#
#856
1#
b00110011 (
b00001100 )
b01011011 *
b10010011 +
#857
0#
#858
1#
b00110000 (
b00001101 )
b01011100 *
b10010100 +
#859
0#
#860
1#
b00101110 (
b00001110 )
b01011101 *
b10010101 +
#861
0#
#862
1#
b00101100 (
b00010000 )
b01011110 *
b10010110 +
#863
0#
#864
1#
b00101001 (
b00010010 )
b01011111 *
b10010111 +
#865
0#
#866
1#
b00100111 (
b00010011 )
b01100000 *
b10011000 +
#867
0#
#868
1#
b00100101 (
b00010101 )
b01100001 *
b10011001 +
#869
0#
#870
1#
b00100011 (
b00010111 )
b01100010 *
b10011010 +
#871
0#
#872
1#
b00100000 (
b00011000 )
b01100011 *
b10011011 +
#873
0#
#874
1#
b00011110 (
b00011010 )
b01100100 *
b10011100 +
#875
0#
#876
1#
b00011100 (
b00011100 )
b01100101 *
b10011101 +
#877
0#
#878
1#
b00011010 (
b00011110 )
b01100110 *
b10011110 +
#879
0#
#880
1#
b00011000 (
b00100000 )
b01100111 *
b10011111 +
#881
0#
#882
1#
b00010111 (
b00100011 )
b01101000 *
b10100000 +
#883
0#
#884
1#
b00010101 (
b00100101 )
b01101001 *
b10100001 +
#885
0#
#886
1#
b00010011 (
b00100111 )
b01101010 *
b10100010 +
#887
0#
#888
1#
b00010010 (
b00101001 )
b01101011 *
b10100011 +
#889
0#
#890
1#
b00010000 (
b00101100 )
b01101100 *
b10100100 +
#891
0#
#892
1#
b00001110 (
b00101110 )
b01101101 *
b10100101 +
#893
0#
#894
1#
b00001101 (
b00110000 )
b01101110 *
b10100110 +
#895
0#
#896
1#
b00001100 (
b00110011 )
b01101111 *
b10100111 +
#897
0#
#898
1#
b00001010 (
b00110101 )
b01110000 *
b10101000 +
#899
0#
#900
1#
b00001001 (
b00111000 )
b01110001 *
b10101001 +
#901
0#
#902
1#
b00001000 (
b00111011 )
b01110010 *
b10101010 +
#903
0#
#904
1#
b00000111 (
b00111101 )
b01110011 *
b10101011 +
#905
0#
#906
1#
b00000110 (
b01000000 )
b01110100 *
b10101100 +
#907
0#
#908
1#
b00000101 (
b01000011 )
b01110101 *
b10101101 +
#909
0#
#910
1#
b00000100 (
b01000101 )
b01110110 *
b10101110 +
#911
0#
#912
1#
b00000011 (
b01001000 )
b01110111 *
b10101111 +
#913
0#
#914
1#
b01001011 )
b01111000 *
b10110000 +
#915
0#
#916
1#
b00000010 (
b01001110 )
b01111001 *
b10110001 +
#917
0#
#918
1#
b00000001 (
b01010001 )
b01111010 *
b10110010 +
#919
0#
#920
1#
b01010100 )
b01111011 *
b10110011 +
#921
0#
#922
1#
b00000000 (
b01010111 )
b01111100 *
b10110100 +
#923
0#
#924
1#
b01011010 )
b01111101 *
b10110101 +
#925
0#
#926
1#
b01011101 )
b01111110 *
b10110110 +
#927
0#
#928
1#
b01100000 )
b01111111 *
b10110111 +
#929
0#
#930
1#
b01100011 )
b10000000 *
b10111000 +
#931
0#
#932
1#
b01100110 )
b10000001 *
b10111001 +
#933
0#
#934
1#
b01101001 )
b10000010 *
b10111010 +
#935
0#
#936
1#
b01101100 )
b10000011 *
b10111011 +
#937
0#
#938
1#
b01101111 )
b10000100 *
b10111100 +
#939
0#
#940
1#
b01110010 )
b10000101 *
b10111101 +
#941
0#
#942
1#
b01110101 )
b10000110 *
b10111110 +
#943
0#
#944
1#
b00000001 (
b01111000 )
b10000111 *
b10111111 +
#945
0#
#946
1#
b01111011 )
b10001000 *
b11000000 +
#947
0#
#948
1#
b00000010 (
b01111111 )
b10001001 *
b11000001 +
#949
0#
#950
1#
b00000011 (
b10000010 )
b10001010 *
b11000010 +
#951
0#
#952
1#
b10000101 )
b10001011 *
b11000011 +
#953
0#
#954
1#
b00000100 (
b10001000 )
b10001100 *
b11000100 +
#955
0#
#956
1#
b00000101 (
b10001011 )
b10001101 *
b11000101 +
#957
0#
#958
1#
b00000110 (
b10001110 )
b10001110 *
b11000110 +
#959
0#
#960
1#
b00000111 (
b10010001 )
b10001111 *
b11000111 +
#961
0#
#962
1#
b00001000 (
b10010100 )
b10010000 *
b11001000 +
#963
0#
#964
1#
b00001001 (
b10010111 )
b10010001 *
b11001001 +
#965
0#
#966
1#
b00001010 (
b10011010 )
b10010010 *
b11001010 +
#967
0#
#968
1#
b00001100 (
b10011101 )
b10010011 *
b11001011 +
#969
0#
#970
1#
b00001101 (
b10100000 )
b10010100 *
b11001100 +
#971
0#
#972
1#
b00001110 (
b10100011 )
b10010101 *
b11001101 +
#973
0#
#974
1#
b00010000 (
b10100110 )
b10010110 *
b11001110 +
#975
0#
#976
1#
b00010010 (
b10101001 )
b10010111 *
b11001111 +
#977
0#
#978
1#
b00010011 (
b10101100 )
b10011000 *
b11010000 +
#979
0#
#980
1#
b00010101 (
b10101111 )
b10011001 *
b11010001 +
#981
0#
#982
1#
b00010111 (
b10110010 )
b10011010 *
b11010010 +
#983
0#
#984
1#
b00011000 (
b10110101 )
b10011011 *
b11010011 +
#985
0#
#986
1#
b00011010 (
b10111000 )
b10011100 *
b11010100 +
#987
0#
#988
1#
b00011100 (
b10111010 )
b10011101 *
b11010101 +
#989
0#
#990
1#
b00011110 (
b10111101 )
b10011110 *
b11010110 +
#991
0#
#992
1#
b00100000 (
b11000000 )
b10011111 *
b11010111 +
#993
0#
#994
1#
b00100011 (
b11000010 )
b10100000 *
b11011000 +
#995
0#
#996
1#
b00100101 (
b11000101 )
b10100001 *
b11011001 +
#997
0#
#998
1#
b00100111 (
b11001000 )
b10100010 *
b11011010 +
#999
0#
#1000
1#
b00101001 (
b11001010 )
b10100011 *
b11011011 +
#1001
0#
#1002
1#
b00101100 (
b11001101 )
b10100100 *
b11011100 +
#1003
0#
#1004
1#
b00101110 (
b11001111 )
b10100101 *
b11011101 +
#1005
0#
#1006
1#
b00110000 (
b11010001 )
b10100110 *
b11011110 +
#1007
0#
#1008
1#
b00110011 (
b11010100 )
b10100111 *
b11011111 +
#1009
0#
#1010
1#
b00110101 (
b11010110 )
b10101000 *
b11100000 +
#1011
0#
#1012
1#
b00111000 (
b11011000 )
b10101001 *
b11100001 +
#1013
0#
#1014
1#
b00111011 (
b11011010 )
b10101010 *
b11100010 +
#1015
0#
#1016
1#
b00111101 (
b11011101 )
b10101011 *
b11100011 +
#1017
0#
#1018
1#
b01000000 (
b11011111 )
b10101100 *
b11100100 +
#1019
0#
#1020
1#
b01000011 (
b11100001 )
b10101101 *
b11100101 +
#1021
0#
#1022
1#
b01000101 (
b11100011 )
b10101110 *
b11100110 +
#1023
0#
#1024
1#
b01001000 (
b11100101 )
b10101111 *
b11100111 +
#1025
0#
#1026
1#
b01001011 (
b11100110 )
b10110000 *
b11101000 +
#1027
0#
#1028
1#
b01001110 (
b11101000 )
b10110001 *
b11101001 +
#1029
0#
#1030
1#
b01010001 (
b11101010 )
b10110010 *
b11101010 +
#1031
0#
#1032
1#
b01010100 (
b11101011 )
b10110011 *
b11101011 +
#1033
0#
#1034
1#
b01010111 (
b11101101 )
b10110100 *
b11101100 +
#1035
0#
#1036
1#
b01011010 (
b11101111 )
b10110101 *
b11101101 +
#1037
0#
#1038
1#
b01011101 (
b11110000 )
b10110110 *
b11101110 +
#1039
0#
#1040
1#
b01100000 (
b11110001 )
b10110111 *
b11101111 +
#1041
0#
#1042
1#
b01100011 (
b11110011 )
b10111000 *
b11110000 +
#1043
0#
#1044
1#
b01100110 (
b11110100 )
b10111001 *
b11110001 +
#1045
0#
#1046
1#
b01101001 (
b11110101 )
b10111010 *
b11110010 +
#1047
0#
#1048
1#
b01101100 (
b11110110 )
b10111011 *
b11110011 +
#1049
0#
#1050
1#
b01101111 (
b11110111 )
b10111100 *
b11110100 +
#1051
0#
#1052
1#
b01110010 (
b11111000 )
b10111101 *
b11110101 +
#1053
0#
#1054
1#
b01110101 (
b11111001 )
b10111110 *
b11110110 +
#1055
0#
#1056
1#
b01111000 (
b11111010 )
b10111111 *
b11110111 +
#1057
0#
#1058
1#
b01111011 (
b11000000 *
b11111000 +
#1059
0#
#1060
1#
b01111111 (
b11111011 )
b11000001 *
b11111001 +
#1061
0#
#1062
1#
b10000010 (
b11111100 )
b11000010 *
b11111010 +
#1063
0#
#1064
1#
b10000101 (
b11000011 *
b11111011 +
#1065
0#
#1066
1#
b10001000 (
b11111101 )
b11000100 *
b11111100 +
#1067
0#
#1068
1#
b10001011 (
b11000101 *
b11111101 +
#1069
0#
#1070
1#
b10001110 (
b11000110 *
b11111110 +
#1071
0#
#1072
1#
b10010001 (
b11000111 *
b11111111 +
#1073
0#
#1074
1#
b10010100 (
b11001000 *
b00000000 +
#1075
0#
#1076
1#
b10010111 (
b11111110 )
b11001001 *
b00000001 +
#1077
0#
#1078
1#
b10011010 (
b11111101 )
b11001010 *
b00000010 +
#1079
0#
#1080
1#
b10011101 (
b11001011 *
b00000011 +
#1081
0#
#1082
1#
b10100000 (
b11001100 *
b00000100 +
#1083
0#
#1084
1#
b10100011 (
b11001101 *
b00000101 +
#1085
0#
#1086
1#
b10100110 (
b11001110 *
b00000110 +
#1087
0#
#1088
1#
b10101001 (
b11111100 )
b11001111 *
b00000111 +
#1089
0#
#1090
1#
b10101100 (
b11010000 *
b00001000 +
#1091
0#
#1092
1#
b10101111 (
b11111011 )
b11010001 *
b00001001 +
#1093
0#
#1094
1#
b10110010 (
b11111010 )
b11010010 *
b00001010 +
#1095
0#
#1096
1#
b10110101 (
b11010011 *
b00001011 +
#1097
0#
#1098
1#
b10111000 (
b11111001 )
b11010100 *
b00001100 +
#1099
0#
#1100
1#
b10111010 (
b11111000 )
b11010101 *
b00001101 +
#1101
0#
#1102
1#
b10111101 (
b11110111 )
b11010110 *
b00001110 +
#1103
0#
#1104
1#
b11000000 (
b11110110 )
b11010111 *
b00001111 +
#1105
0#
#1106
1#
b11000010 (
b11110101 )
b11011000 *
b00010000 +
#1107
0#
#1108
1#
b11000101 (
b11110100 )
b11011001 *
b00010001 +
#1109
0#
#1110
1#
b11001000 (
b11110011 )
b11011010 *
b00010010 +
#1111
0#
#1112
1#
b11001010 (
b11110001 )
b11011011 *
b00010011 +
#1113
0#
#1114
1#
b11001101 (
b11110000 )
b11011100 *
b00010100 +
#1115
0#
#1116
1#
b11001111 (
b11101111 )
b11011101 *
b00010101 +
#1117
0#
#1118
1#
b11010001 (
b11101101 )
b11011110 *
b00010110 +
#1119
0#
#1120
1#
b11010100 (
b11101011 )
b11011111 *
b00010111 +
#1121
0#
#1122
1#
b11010110 (
b11101010 )
b11100000 *
b00011000 +
#1123
0#
#1124
1#
b11011000 (
b11101000 )
b11100001 *
b00011001 +
#1125
0#
